[
    {
        "name": "Afton Alps",
        "condition": "Closed",
        "comments": "...",
        "username": "bigwheel",
        "timestamp": "08-19-2019, 09:20 AM",
        "parsedTimestamp": "6 months ago",
        "location": "Hastings",
        "trailforksMapId": ""
    },
    {
        "name": "Battle Creek",
        "condition": "Closed",
        "comments": "Once snow has fallen and been groomed, Battle Creek closes for the season.  Enjoy the other trails!!",
        "username": "Pandl",
        "timestamp": "11-29-2019, 11:48 AM",
        "parsedTimestamp": "3 months ago",
        "location": "St. Paul",
        "trailforksMapId": "5538"
    },
    {
        "name": "Monticello",
        "condition": "Melting Do Not Ride",
        "comments": "Warm weather will be melting things out at the trail.  Let's stay off when it is soft so we might po...",
        "username": "Count",
        "timestamp": "02-21-2020, 03:45 PM",
        "parsedTimestamp": "4 days ago",
        "location": "Monticello",
        "trailforksMapId": "13706"
    },
    {
        "name": "Carver Lake",
        "condition": "Closed",
        "comments": "It\u0092s going to hit 45 degrees today. Trail is closed all day. Please do not ride!",
        "username": "mtb_guy",
        "timestamp": "02-22-2020, 11:36 AM",
        "parsedTimestamp": "3 days ago",
        "location": "Woodbury",
        "trailforksMapId": "9243"
    },
    {
        "name": "Cottage Grove Bike Park",
        "condition": "Closed",
        "comments": "Closed (\"All tucked in...\" per their Instagram page).",
        "username": "zeronine3",
        "timestamp": "11-27-2019, 10:26 PM",
        "parsedTimestamp": "3 months ago",
        "location": "Cottage Grove",
        "trailforksMapId": ""
    },
    {
        "name": "Elm Creek",
        "condition": "Closed",
        "comments": "Closing down while melting",
        "username": "gi02sl",
        "timestamp": "02-23-2020, 10:48 AM",
        "parsedTimestamp": "2 days ago",
        "location": "Maple Grove",
        "trailforksMapId": "5543"
    },
    {
        "name": "Hillside Park",
        "condition": "Packed",
        "comments": "Trail is open.  Just had time to peek at the entrance and exit, a few hikers were out in the warm we...",
        "username": "Count",
        "timestamp": "02-24-2020, 08:07 PM",
        "parsedTimestamp": "Yesterday",
        "location": "Elk River",
        "trailforksMapId": "7593"
    },
    {
        "name": "Lake Rebecca",
        "condition": "Closed",
        "comments": "Closed until midweek most likely. We\u0092ll see what happens. But until then, please stay off the trail....",
        "username": "cadaverbones",
        "timestamp": "02-22-2020, 12:13 PM",
        "parsedTimestamp": "3 days ago",
        "location": "Hastings",
        "trailforksMapId": "12004"
    },
    {
        "name": "Lebanon Hills",
        "condition": "Melting Do Not Ride",
        "comments": "The trail is now mashed potatoes.  Please stay off until the the temps are solidly below freezing.",
        "username": "tedsti",
        "timestamp": "02-23-2020, 11:54 AM",
        "parsedTimestamp": "2 days ago",
        "location": "Eagan",
        "trailforksMapId": "3438"
    },
    {
        "name": "MN River Bottoms",
        "condition": "Melting Do Not Ride",
        "comments": "Getting soft, muddy quick. Be good trail stewards for the refreeze next week. I left trail at 10:30a...",
        "username": "Safe-T-Guy",
        "timestamp": "02-22-2020, 01:03 PM",
        "parsedTimestamp": "3 days ago",
        "location": "Bloomington",
        "trailforksMapId": "25053"
    },
    {
        "name": "Murphy Hanrehan",
        "condition": "Closed",
        "comments": "Closed for melting conditions.  This might be a few days.",
        "username": "journeyman",
        "timestamp": "02-22-2020, 11:32 AM",
        "parsedTimestamp": "3 days ago",
        "location": "Savage",
        "trailforksMapId": "7646"
    },
    {
        "name": "Salem Hills",
        "condition": "Fat Tires",
        "comments": "Trail was packed in great shape, only slightly icy (studs helpful, but not required) before today's ...",
        "username": "wingfwd",
        "timestamp": "12-09-2019, 01:49 PM",
        "parsedTimestamp": "2 months ago",
        "location": "Inver Grove Heights",
        "trailforksMapId": "12008"
    },
    {
        "name": "Terrace Oaks",
        "condition": "Closed",
        "comments": "The dirt riding season is over.  Terrace Oaks is NOT groomed or maintained in any way for winter rid...",
        "username": "jeffgude",
        "timestamp": "11-27-2019, 03:22 PM",
        "parsedTimestamp": "3 months ago",
        "location": "Burnsville",
        "trailforksMapId": "12011"
    },
    {
        "name": "Theodore Wirth",
        "condition": "Closed",
        "comments": "Gates are closed. All MOCA/MORC Trails At Theo are closed.   This closure will last until temperatur...",
        "username": "SIM",
        "timestamp": "02-22-2020, 12:15 PM",
        "parsedTimestamp": "3 days ago",
        "location": "Golden Valley",
        "trailforksMapId": "9224"
    },
    {
        "name": "7-Mile",
        "condition": "Fat Tires",
        "comments": "Trails are great. Fat tires or studs recommended. Some icy spots and the water crossings are startin...",
        "username": "3rdgeer",
        "timestamp": "12-09-2017, 09:45 AM",
        "parsedTimestamp": "3 years ago",
        "location": "Minneapolis",
        "trailforksMapId": ""
    },
    {
        "name": "Fort LeHillier",
        "condition": "Closed",
        "comments": "Fort LeHillier's one mile trail is not currently being maintained by MAMB, therefore, is closed. Ple...",
        "username": "M.A.M.B.",
        "timestamp": "05-19-2017, 05:01 AM",
        "parsedTimestamp": "3 years ago",
        "location": "Mankato",
        "trailforksMapId": ""
    },
    {
        "name": "Holzinger Lodge",
        "condition": "Tacky",
        "comments": "Rode Saturday afternoon and the trail was in great shape!",
        "username": "Farmer's Tan",
        "timestamp": "05-12-2019, 08:08 PM",
        "parsedTimestamp": "9 months ago",
        "location": "Winona",
        "trailforksMapId": "10305"
    },
    {
        "name": "Mt. Kato",
        "condition": "Tacky",
        "comments": "Mt. Kato is rocking this year!!!  Thanks to John R. at Mt. Kato and MAMB volunteers, trails are gett...",
        "username": "M.A.M.B.",
        "timestamp": "06-30-2019, 11:44 AM",
        "parsedTimestamp": "8 months ago",
        "location": "Mankato",
        "trailforksMapId": "22512"
    },
    {
        "name": "Memorial Trail",
        "condition": "Tacky",
        "comments": "Trail is in great condition Rode Saturday with the kids, all the Blue is great.  Someone has been we...",
        "username": "SKullman",
        "timestamp": "07-15-2019, 09:36 AM",
        "parsedTimestamp": "7 months ago",
        "location": "Red Wing",
        "trailforksMapId": "13282"
    },
    {
        "name": "Grand Rapids",
        "condition": "Damp",
        "comments": "Many new trails in the Tioga (Cohasset) Area. Worth the trip if you have a day.",
        "username": "Roadsalt",
        "timestamp": "10-26-2019, 11:00 AM",
        "parsedTimestamp": "4 months ago",
        "location": "Grand Rapids",
        "trailforksMapId": "14550"
    },
    {
        "name": "Jail Trail",
        "condition": "Fat Tires",
        "comments": "Trail was groomed tonight. Should set up nicely by morning.",
        "username": "rath",
        "timestamp": "12-01-2019, 10:13 PM",
        "parsedTimestamp": "2 months ago",
        "location": "St Cloud",
        "trailforksMapId": "7592"
    },
    {
        "name": "Milaca",
        "condition": "Tacky",
        "comments": "Rode yesterday(6/20) late evening. Trails were in very good condition with very few damp spots. Litt...",
        "username": "SnoSkinz",
        "timestamp": "06-21-2017, 10:14 AM",
        "parsedTimestamp": "3 years ago",
        "location": "Milaca",
        "trailforksMapId": ""
    },
    {
        "name": "Hartley Park",
        "condition": "Dry",
        "comments": "Open for the season!   Please always check the COGGS website (www.coggs.com) for most cur...",
        "username": "namdoogttam",
        "timestamp": "05-10-2017, 11:31 AM",
        "parsedTimestamp": "3 years ago",
        "location": "Duluth",
        "trailforksMapId": "7575"
    },
    {
        "name": "Piedmont Trail",
        "condition": "Damp",
        "comments": "Please always check the COGGS website (www.coggs.com) for most current, day-to-day trail ...",
        "username": "namdoogttam",
        "timestamp": "05-10-2017, 11:36 AM",
        "parsedTimestamp": "3 years ago",
        "location": "Duluth",
        "trailforksMapId": "9224"
    },
    {
        "name": "Whitetail Ridge",
        "condition": "Tacky",
        "comments": "Tacky to greasy.  A few wet spots, but overall good.",
        "username": "Pandl",
        "timestamp": "08-17-2019, 01:37 PM",
        "parsedTimestamp": "6 months ago",
        "location": "River Falls,",
        "trailforksMapId": "19492"
    },
    {
        "name": "Woolly Trail",
        "condition": "Melting Do Not Ride",
        "comments": "Trails were pretty soft by 10am, trails closed until Monday morning.",
        "username": "Arron",
        "timestamp": "02-23-2020, 10:39 AM",
        "parsedTimestamp": "2 days ago",
        "location": "St. Croix, WI",
        "trailforksMapId": "19492"
    },
    {
        "name": "Levis Trow",
        "condition": "Tacky",
        "comments": "Lots of great trails out here. Cliffhanger is one of a kind. Lots of leaves though.",
        "username": "Roadsalt",
        "timestamp": "10-26-2019, 10:58 AM",
        "parsedTimestamp": "4 months ago",
        "location": "Neillsville, WI",
        "trailforksMapId": "12627"
    }
]